LICENSE
README.md
setup.cfg
setup.py
festpay_sdk.egg-info/PKG-INFO
festpay_sdk.egg-info/SOURCES.txt
festpay_sdk.egg-info/dependency_links.txt
festpay_sdk.egg-info/top_level.txt
payment_page_sdk/__init__.py
payment_page_sdk/callback.py
payment_page_sdk/gate.py
payment_page_sdk/payment.py
payment_page_sdk/payment_page.py
payment_page_sdk/process_exception.py
payment_page_sdk/signature_handler.py