Metadata-Version: 2.1
Name: festpay-sdk
Version: 1.0.1
Summary: UNKNOWN
Home-page: https://github.com/festpay/paymentpage-sdk-python
Author-email: sdk@festpay.ru
License: MIT
Platform: UNKNOWN
Classifier: Development Status :: 3 - Alpha
Classifier: Intended Audience :: Developers
Classifier: License :: OSI Approved :: MIT License
Classifier: Programming Language :: Python :: 3.5
Classifier: Programming Language :: Python :: 3.6
Classifier: Programming Language :: Python :: 3.7
Classifier: Programming Language :: Python :: 3.8
Classifier: Topic :: Software Development :: Libraries :: Python Modules
License-File: LICENSE
